rag_citation/__init__.py
rag_citation/cite_item.py
rag_citation/inference.py
rag_citation/schema.py
rag_citation/base_model/__init__.py
rag_citation/base_model/base.py
rag_citation/base_model/embedding_model.py
rag_citation/base_model/spacy_model.py
rag_citation/focus_word/__init__.py
rag_citation/focus_word/focus_word.py
rag_citation/focus_word/schema.py
rag_citation/pair/__init__.py
rag_citation/pair/focus_word_in_cite_data.py
rag_citation/pair/generate_pair.py
rag_citation/pair/schema.py
rag_citation/score/__init__.py
rag_citation/score/score.py
rag_citation-0.0.5.dist-info/LICENSE
rag_citation-0.0.5.dist-info/METADATA
rag_citation-0.0.5.dist-info/WHEEL
rag_citation-0.0.5.dist-info/top_level.txt
rag_citation-0.0.5.dist-info/RECORD
