Metadata-Version: 2.1
Name: rag_citation
Version: 0.0.5
Summary: RAG Citation is an project that combines Retrieval-Augmented Generation (RAG) with automatic citation generation. This tool is designed to enhance the credibility of AI-generated content by providing relevant citations for the information used in generating responses.
Home-page: https://github.com/rahulanand1103/rag-citation
Author: rahul anand
Author-email: rahulanand1103@gmail.com
License: MIT
Requires-Python: >=3.8
License-File: LICENSE
Requires-Dist: spacy ==3.7.5
Requires-Dist: sentence-transformers ==3.0.1
